fuzzy_match/__init__.py
fuzzy_match/algorithims.py
fuzzy_match/match.py
fuzzy_match-0.0.1.dist-info/LICENSE
fuzzy_match-0.0.1.dist-info/METADATA
fuzzy_match-0.0.1.dist-info/WHEEL
fuzzy_match-0.0.1.dist-info/top_level.txt
fuzzy_match-0.0.1.dist-info/RECORD
