Metadata-Version: 2.1
Name: fuzzy-match
Version: 0.0.1
Summary: Fuzzy string matching in Python
Home-page: https://github.com/darwinagain/fuzzy-match
Author: darwinagain
Author-email: iamdarwinagain@gmail.com
License: MIT
Platform: UNKNOWN
Classifier: License :: OSI Approved :: MIT License
Classifier: Programming Language :: Python :: 3
Classifier: Programming Language :: Python :: 3.7
